MANIFEST.in
README.txt
setup.py
docs/HISTORY.txt
docs/html/api-objects.txt
docs/html/class-tree.html
docs/html/exceptions.AssertionError-class.html
docs/html/frames.html
docs/html/help.html
docs/html/identifier-index.html
docs/html/index.html
docs/html/module-tree.html
docs/html/nsi.granulate-module.html
docs/html/nsi.granulate-pysrc.html
docs/html/nsi.granulate.FileUtils-module.html
docs/html/nsi.granulate.FileUtils-pysrc.html
docs/html/nsi.granulate.FileUtils.File-class.html
docs/html/nsi.granulate.GranularUtils-module.html
docs/html/nsi.granulate.GranularUtils-pysrc.html
docs/html/nsi.granulate.GranularUtils.Grain-class.html
docs/html/nsi.granulate.Granulate'-module.html
docs/html/nsi.granulate.Granulate'-pysrc.html
docs/html/nsi.granulate.Granulate'.Granulate-class.html
docs/html/nsi.granulate.GranulateOffice'-module.html
docs/html/nsi.granulate.GranulateOffice'-pysrc.html
docs/html/nsi.granulate.GranulateOffice'.ConectionServerError-class.html
docs/html/nsi.granulate.GranulateOffice'.GranulateOffice-class.html
docs/html/nsi.granulate.GranulatePDF'-module.html
docs/html/nsi.granulate.GranulatePDF'-pysrc.html
docs/html/nsi.granulate.GranulatePDF'.ErrorXmlto-class.html
docs/html/nsi.granulate.GranulatePDF'.GranulatePDF-class.html
docs/html/nsi.granulate.GranulatePDF'.PyPdf2TableError-class.html
docs/html/nsi.granulate.template-module.html
docs/html/nsi.granulate.template-pysrc.html
docs/html/nsi.granulate.tests-module.html
docs/html/nsi.granulate.tests-pysrc.html
docs/html/nsi.granulate.tests.data-module.html
docs/html/nsi.granulate.tests.data-pysrc.html
docs/html/nsi.granulate.tests.testGranulate-module.html
docs/html/nsi.granulate.tests.testGranulate-pysrc.html
docs/html/nsi.granulate.tests.testGranulate.TestGranulate-class.html
docs/html/nsi.granulate.tests.testGranulateDOC-module.html
docs/html/nsi.granulate.tests.testGranulateDOC-pysrc.html
docs/html/nsi.granulate.tests.testGranulateDOC.TestGranulate-class.html
nsi.granulate.egg-info/PKG-INFO
nsi.granulate.egg-info/SOURCES.txt
nsi.granulate.egg-info/dependency_links.txt
nsi.granulate.egg-info/entry_points.txt
nsi.granulate.egg-info/namespace_packages.txt
nsi.granulate.egg-info/not-zip-safe
nsi.granulate.egg-info/requires.txt
nsi.granulate.egg-info/top_level.txt
