Metadata-Version: 1.0
Name: nsi.granulate
Version: 1.0.3
Summary: Granulate Content
Home-page: UNKNOWN
Author: Ronaldo Amaral Santos / NSI - CEFETCampos
Author-email: ronaldinho.as@gmail.com
License: GPL
Platform: UNKNOWN
Classifier: Programming Language :: Python
Classifier: Topic :: Software Development :: Libraries :: Python Modules
